sphinx_cli/__init__.py
sphinx_cli/runner.py
sphinx_cli/sphinx-cli.cjs
sphinx_ai_cli-1.0.0.dist-info/METADATA
sphinx_ai_cli-1.0.0.dist-info/WHEEL
sphinx_ai_cli-1.0.0.dist-info/entry_points.txt
sphinx_ai_cli-1.0.0.dist-info/top_level.txt
sphinx_ai_cli-1.0.0.dist-info/RECORD
